sujuster/__init__.py
sujuster/__main__.py
sujuster/sujust.py
sujuster-1.1.0.dist-info/LICENSE
sujuster-1.1.0.dist-info/METADATA
sujuster-1.1.0.dist-info/WHEEL
sujuster-1.1.0.dist-info/entry_points.txt
sujuster-1.1.0.dist-info/top_level.txt
sujuster-1.1.0.dist-info/RECORD
