Metadata-Version: 2.1
Name: sujuster
Version: 1.1.0
Summary: The SUbtitle adJUSTER - adjust offsets of a .srt subtitle file
Home-page: https://github.com/flypenguin/python-sujuster
Download-URL: https://github.com/flypenguin/python-sujuster/tarball/1.1.0
Author: Axel Bock
Author-email: mr.axel.bock@gmail.com
Keywords: subtitles srt script
Classifier: License :: OSI Approved :: MIT License
Classifier: Development Status :: 5 - Production/Stable
Classifier: Intended Audience :: End Users/Desktop
Classifier: Programming Language :: Python :: 3
Classifier: Programming Language :: Python :: 2
Classifier: Operating System :: POSIX
Classifier: Operating System :: MacOS
Classifier: Topic :: Text Processing :: Filters
Classifier: Topic :: Utilities
License-File: LICENSE
